simplegen/__init__.py
simplegen/cli.py
simplegen/simplegen.py
simplegen-1.0.1.dist-info/DESCRIPTION.rst
simplegen-1.0.1.dist-info/METADATA
simplegen-1.0.1.dist-info/RECORD
simplegen-1.0.1.dist-info/WHEEL
simplegen-1.0.1.dist-info/entry_points.txt
simplegen-1.0.1.dist-info/metadata.json
simplegen-1.0.1.dist-info/top_level.txt
