Metadata-Version: 2.0
Name: simplegen
Version: 1.0.1
Summary: Simple site generator.
Home-page: https://github.com/mohamed-aziz/simplegen
Author: Mohamed Aziz Knani
Author-email: medazizknani@gmail.com
License: GPLV3
Keywords: static website generator simple markdown
Platform: UNKNOWN
Classifier: Development Status :: 3 - Alpha
Classifier: Intended Audience :: Developers
Classifier: Topic :: Software Development :: Build Tools
Classifier: License :: OSI Approved :: GNU General Public License v3 (GPLv3)
Classifier: Programming Language :: Python :: 2
Classifier: Programming Language :: Python :: 2.7
Classifier: Programming Language :: Python :: 3
Classifier: Programming Language :: Python :: 3.4
Classifier: Programming Language :: Python :: 3.5
Classifier: Programming Language :: Python :: 3.6
Requires-Dist: Jinja2 (==2.8)
Requires-Dist: Markdown (==2.6.7)
Requires-Dist: click (==6.6)
Requires-Dist: colorama (==0.3.7)
Requires-Dist: htmlmin (==0.1.10)
Requires-Dist: pytest (==3.0.4)
Requires-Dist: python-markdown-math (==0.3)
Requires-Dist: six (==1.10.0)
